astro_tigress/__init__.py
astro_tigress/athena_read.py
astro_tigress/const.py
astro_tigress/coolftn.txt
astro_tigress/map_circular_beam.py
astro_tigress/radmc.py
astro_tigress/synthetic_HI.py
astro_tigress/synthetic_dustpol.py
astro_tigress/tigress_read.py
astro_tigress/tigress_utils.py
astro_tigress/ytathena.py
astro_tigress-0.1.5.dist-info/WHEEL
astro_tigress-0.1.5.dist-info/METADATA
astro_tigress-0.1.5.dist-info/RECORD
