Metadata-Version: 2.1
Name: astro-tigress
Version: 0.1.5
Summary: TIGRESS data release and associate python scripts
Author: Chang-Goo Kim
Author-email: cgkim@astro.princeton.edu
Requires-Python: >=3.7,<3.11
Classifier: Programming Language :: Python :: 3
Classifier: Programming Language :: Python :: 3.10
Classifier: Programming Language :: Python :: 3.7
Classifier: Programming Language :: Python :: 3.8
Classifier: Programming Language :: Python :: 3.9
Requires-Dist: astropy (>=5.1,<6.0)
Requires-Dist: h5py (>=3.7.0,<4.0.0)
Requires-Dist: matplotlib (>=3.5.2,<4.0.0)
Requires-Dist: numpy (>=1.20.0,<2.0.0)
Requires-Dist: scipy (>=1.8.1,<2.0.0)
Requires-Dist: urllib3 (>=1.21.1,<2.0.0)
Requires-Dist: xarray (==0.20.0)
Requires-Dist: yt (>=4.0.4,<5.0.0)
